README.md
setup.py
Flask_Philo_SQLAlchemy.egg-info/PKG-INFO
Flask_Philo_SQLAlchemy.egg-info/SOURCES.txt
Flask_Philo_SQLAlchemy.egg-info/dependency_links.txt
Flask_Philo_SQLAlchemy.egg-info/entry_points.txt
Flask_Philo_SQLAlchemy.egg-info/requires.txt
Flask_Philo_SQLAlchemy.egg-info/top_level.txt
flask_philo_sqlalchemy/__init__.py
flask_philo_sqlalchemy/connection.py
flask_philo_sqlalchemy/exceptions.py
flask_philo_sqlalchemy/http.py
flask_philo_sqlalchemy/orm.py
flask_philo_sqlalchemy/schema.py
flask_philo_sqlalchemy/test.py
flask_philo_sqlalchemy/types.py